openicite/__init__.py
openicite-0.1.6.dist-info/LICENSE
openicite-0.1.6.dist-info/METADATA
openicite-0.1.6.dist-info/WHEEL
openicite-0.1.6.dist-info/top_level.txt
openicite-0.1.6.dist-info/RECORD
