Metadata-Version: 2.1
Name: openicite
Version: 0.1.6
Summary: A python wrapper for interacting with the iCite API
Author-email: phage-GP <mirscope@outlook.com>
Project-URL: Homepage, https://github.com/opendoicom/openicite/
Project-URL: Issues, https://github.com/opendoicom/openicite/issues
Classifier: Programming Language :: Python :: 3
Classifier: License :: OSI Approved :: MIT License
Classifier: Operating System :: OS Independent
Requires-Python: >=3.6
License-File: LICENSE
Requires-Dist: requests
